ai4data/__init__.py
ai4data/commons.py
ai4data/config.py
ai4data/indexing/embed.py
ai4data/indexing/index.py
ai4data/metadata/handler.py
ai4data/metadata/templates/document_page_content.jinja2
ai4data/metadata/templates/indicator_page_content.jinja2
ai4data/metadata/templates/render.py
ai4data/metadata/utils.py
ai4data/methods/semantic_cluster_embedding.py
ai4data/paths.py
ai4data/processors/document.py
ai4data/scraper/document.py
ai4data/scraper/metadata.py
ai4data/services/search.py
ai4data-0.0.1.dist-info/LICENSE
ai4data-0.0.1.dist-info/METADATA
ai4data-0.0.1.dist-info/WHEEL
ai4data-0.0.1.dist-info/RECORD
