Metadata-Version: 2.1
Name: ai4data
Version: 0.0.1
Summary: 
Author: Aivin V. Solatorio
Author-email: avsolatorio@gmail.com
Requires-Python: >=3.10,<4.0
Classifier: Programming Language :: Python :: 3
Classifier: Programming Language :: Python :: 3.10
Classifier: Programming Language :: Python :: 3.11
Requires-Dist: backoff (>=2.2.1,<3.0.0)
Requires-Dist: bs4 (>=0.0.2,<0.0.3)
Requires-Dist: fire (>=0.6.0,<0.7.0)
Requires-Dist: jq (>=1.7.0,<2.0.0)
Requires-Dist: langchain-community (>=0.2.1,<0.3.0)
Requires-Dist: langchain-huggingface (>=0.0.1,<0.0.2)
Requires-Dist: langchain-qdrant (>=0.1.3,<0.2.0)
Requires-Dist: prefect (>=2.19.3,<3.0.0)
Requires-Dist: pymupdf (>=1.24.5,<2.0.0)
Requires-Dist: qdrant-client (>=1.9.1,<2.0.0)
Requires-Dist: sentence-transformers (>=3.0.0,<4.0.0)
Requires-Dist: tika (>=2.6.0,<3.0.0)
Requires-Dist: tqdm (>=4.66.4,<5.0.0)
